{
  "id": "Sableye",
  "spawnInfos": [
    {
      "spec": "species:Sableye",
      "stringLocationTypes": [
        "Underground"
      ],
      "minLevel": 10,
      "maxLevel": 35,
      "typeID": "pokemon",
      "heldItems": [
        {
          "itemID": "pixelmon:wide_lens",
          "percentChance": 5
        }
      ],
      "condition": {
        "maxY": 60
      },
      "anticondition": {
        "stringBiomes": [
          "ultra space"
        ]
      },
      "rarityMultipliers": [
        {
          "multiplier": 2,
          "condition": {
            "neededNearbyBlocks": [
              "minecraft:planks"
            ]
          }
        }
      ],
      "rarity": 30.0
    },
    {
      "spec": "species:Sableye",
      "stringLocationTypes": [
        "Land"
      ],
      "minLevel": 10,
      "maxLevel": 35,
      "typeID": "pokemon",
      "heldItems": [
        {
          "itemID": "pixelmon:wide_lens",
          "percentChance": 5
        }
      ],
      "condition": {
        "stringBiomes": [
          "hellish",
          "pixelmon:ultra_deep_sea"
        ]
      },
      "rarity": 30.0
    },
    {
      "spec": "species:Sableye palette:drowned",
      "stringLocationTypes": [
        "Water"
      ],
      "minLevel": 10,
      "maxLevel": 35,
      "typeID": "pokemon",
      "heldItems": [
        {
          "itemID": "pixelmon:wide_lens",
          "percentChance": 5
        }
      ],
      "condition": {
        "stringBiomes": [
          "drowned"
        ]
      },
      "rarity": 20.0
    }
  ]
}
